{
  "success": false,
  "message": "test \"todos_crud\" failed at step \"create\"",
  "test_name": "todos_crud",
  "run_id": "tr_jvza7834",
  "run": {
    "run_id": "tr_jvza7834",
    "test_name": "todos_crud",
    "flow_name": "todos_crud",
    "generated_at": "2026-06-25T13:46:05Z",
    "environment": "dev",
    "triggered_by": "manual",
    "tags": [],
    "api": {
      "name": "Supabase Todos API",
      "base_url": "https://tvlphasahvaffdzzgugf.supabase.co",
      "version": "v1",
      "auth_scheme": "bearer"
    }
  },
  "assertions": [
    {
      "id": "s1",
      "label": "create status",
      "expression": "= 201",
      "passed": false,
      "error_message": "expected status 201, got 401"
    }
  ],
  "state": {
    "resolved": {},
    "created_ids": [],
    "last_step": "create"
  },
  "steps": [
    {
      "step": "create",
      "action": "create_todo",
      "method": "POST",
      "status_code": 401,
      "expected_status": 201,
      "passed": false,
      "duration_ms": 1378,
      "request_size_bytes": 116,
      "response_size_bytes": 70,
      "error_message": "expected status 201, got 401",
      "request_url": "https://tvlphasahvaffdzzgugf.supabase.co/rest/v1/todos",
      "request_body": {
        "description": "Created from contract E2E flow",
        "title": "E2E Todo",
        "user_id": "5cb5b240-8bd4-4172-a219-e7561214697a"
      },
      "response_body": {
        "code": "PGRST303",
        "details": null,
        "hint": null,
        "message": "JWT expired"
      },
      "request_model": "TodoCreate",
      "response_model": "TodoList",
      "response_headers": {
        "Alt-Svc": "h3=\":443\"; ma=86400",
        "Cf-Cache-Status": "DYNAMIC",
        "Cf-Ray": "a1146a74786a01e1-IAD",
        "Content-Length": "70",
        "Content-Type": "application/json; charset=utf-8",
        "Date": "Thu, 25 Jun 2026 13:46:01 GMT",
        "Proxy-Status": "PostgREST; error=PGRST303",
        "Sb-Gateway-Version": "1",
        "Sb-Project-Ref": "tvlphasahvaffdzzgugf",
        "Sb-Request-Id": "019eff07-c4f0-76d0-b4a8-fb20a28e5427",
        "Server": "cloudflare",
        "Set-Cookie": "__cf_bm=lULRTYtbZLgudERyb4HkSbhyhaCy30Dl7xFcjD85c9A-1782395159.7685788-1.0.1.1-5SabIWrOWeczcQAnSeOcnyU9ASIh_jygqX4PQoe46wJKnWX00rO2hNDxKGlf1qVkjdMiR0YJIA.iP4jn7ejHRnPmrK5AUuk_awF_3fzFZ6OSE7nQWmxzPf33HK6kPPmv; HttpOnly; SameSite=None; Secure; Path=/; Domain=supabase.co; Expires=Thu, 25 Jun 2026 14:16:01 GMT",
        "Strict-Transport-Security": "max-age=31536000; includeSubDomains; preload",
        "Www-Authenticate": "Bearer error=\"invalid_token\", error_description=\"JWT expired\"",
        "X-Content-Type-Options": "nosniff",
        "X-Envoy-Attempt-Count": "1",
        "X-Envoy-Upstream-Service-Time": "77"
      }
    }
  ],
  "summary": {
    "total_steps": 1,
    "passed_steps": 0,
    "failed_steps": 1,
    "total_assertions": 1,
    "passed_assertions": 0,
    "failed_assertions": 1,
    "total_duration_ms": 1378,
    "slowest_step": "create",
    "p50_ms": 1378,
    "p95_ms": 1378,
    "success": false,
    "failure_reason": "test \"todos_crud\" failed at step \"create\"",
    "first_failure_step": "create"
  },
  "models": {
    "Empty": {
      "description": "No response body (204 delete)."
    },
    "Todo": {
      "created_at": "datetime",
      "description": "Single todo row.",
      "id": "uuid",
      "title": "string",
      "user_id": "uuid"
    },
    "TodoCreate": {
      "description": "Payload for creating a todo.",
      "required": [
        "title",
        "user_id"
      ],
      "title": "string",
      "user_id": "uuid"
    },
    "TodoList": {
      "description": "Array of todos returned by PostgREST.",
      "items": "Todo",
      "type": "array"
    },
    "TodoUpdate": {
      "description": "Payload for updating a todo.",
      "title": "string"
    }
  },
  "route_schemas": {
    "create_todo": {
      "request_body": "TodoCreate",
      "responses": {
        "201": "TodoList"
      }
    },
    "delete_todo": {
      "responses": {
        "204": "Empty"
      }
    },
    "get_todo": {
      "responses": {
        "200": "TodoList"
      }
    },
    "list_todos": {
      "responses": {
        "200": "TodoList"
      }
    },
    "update_todo": {
      "request_body": "TodoUpdate",
      "responses": {
        "200": "TodoList"
      }
    }
  }
}